acdh_django_sirad-0.1.0.dist-info/METADATA
acdh_django_sirad-0.1.0.dist-info/RECORD
acdh_django_sirad-0.1.0.dist-info/WHEEL
acdh_django_sirad-0.1.0.dist-info/top_level.txt
sirad/__init__.py
sirad/apps.py
sirad/code_templates.py
sirad/sirad.py
